lunamath/__init__.py
lunamath-0.0.1.dist-info/LICENSE.txt
lunamath-0.0.1.dist-info/METADATA
lunamath-0.0.1.dist-info/WHEEL
lunamath-0.0.1.dist-info/top_level.txt
lunamath-0.0.1.dist-info/RECORD
