Metadata-Version: 2.1
Name: lunamath
Version: 0.0.1
Summary: mathmatics functions
Home-page: https://github.com/GuilhermeLunetta/
Author: Guilherme Lunetta
Author-email: guilunetta@hotmail.com
License: UNKNOWN
Platform: UNKNOWN
Classifier: Programming Language :: Python :: 3
Classifier: License :: OSI Approved :: MIT License
Classifier: Operating System :: OS Independent
